djcroco
