Metadata-Version: 1.0
Name: djcroco
Version: 0.3.1
Summary: UNKNOWN
Home-page: https://github.com/mattack108/djcroco/
Author: Matt Lenc
Author-email: matt.lenc@gmail.com
License: UNKNOWN
Platform: UNKNOWN
